vizlook/__init__.py
vizlook/_client.py
vizlook/_exceptions.py
vizlook/_types.py
vizlook/_version.py
vizlook-0.1.1.dist-info/LICENSE
vizlook-0.1.1.dist-info/METADATA
vizlook-0.1.1.dist-info/WHEEL
vizlook-0.1.1.dist-info/RECORD
