Metadata-Version: 2.3
Name: vizlook
Version: 0.1.1
Summary: The official Python library for the Vizlook API
License: MIT
Author: Vizlook
Author-email: support@vizlook.com
Requires-Python: >=3.9
Classifier: Programming Language :: Python :: 3.9
Classifier: Programming Language :: Python :: 3.10
Classifier: Programming Language :: Python :: 3.11
Classifier: Programming Language :: Python :: 3.12
Classifier: Programming Language :: Python :: 3.13
Classifier: Operating System :: OS Independent
Classifier: Operating System :: POSIX
Classifier: Operating System :: MacOS
Classifier: Operating System :: POSIX :: Linux
Requires-Dist: httpx (>=0.28.1,<0.29.0)
Requires-Dist: pydantic (>=2.11.7,<3.0.0)
Project-URL: Homepage, https://github.com/vizlook/vizlook-python
Project-URL: Repository, https://github.com/vizlook/vizlook-python
